spacebee_commander/__init__.py
spacebee_commander/app.py
spacebee_commander/commander.py
spacebee_commander/commands_loader.py
spacebee_commander/communication.py
spacebee_commander/message_manager.py
spacebee_commander/network_parameters.py
spacebee_commander/telecommand_interface.py
spacebee_commander-0.2.0.dist-info/METADATA
spacebee_commander-0.2.0.dist-info/WHEEL
spacebee_commander-0.2.0.dist-info/entry_points.txt
spacebee_commander-0.2.0.dist-info/licenses/LICENSE
spacebee_commander-0.2.0.dist-info/RECORD
